{"bindings":[{"action":"CharacterController/Move","id":"38a55dc9-cbac-460e-bd49-475af9234918","path":"<Keyboard>/d","interactions":"null","processors":"null"},{"action":"CharacterController/Move","id":"460d13b0-4daa-45e1-a496-effd030ef224","path":"<Keyboard>/f","interactions":"null","processors":"null"},{"action":"CharacterController/FirstAttack","id":"7c1e0495-da89-4075-ae98-674952ecbbf6","path":"<Keyboard>/y","interactions":"null","processors":"null"},{"action":"CharacterController/SecondAttack","id":"64af0266-0d8c-4fd1-b999-267f712415db","path":"<Keyboard>/g","interactions":"null","processors":"null"}]}